{
  "students": [
    {
      "id": "2",
      "firstname": "Tom",
      "lastname": "Smith",
      "group": "React N34"
    },
    {
      "id": "3",
      "firstname": "John",
      "lastname": "Smith",
      "group": "React N45"
    },
    {
      "id": "4",
      "firstname": "John",
      "lastname": "White",
      "group": "React N45"
    },
    {
      "id": "5",
      "firstname": "Tom",
      "lastname": "Smith",
      "group": "React N34"
    },
    {
      "id": "6",
      "firstname": "John",
      "lastname": "Smith",
      "group": "React N45"
    },
    {
      "id": "7",
      "firstname": "John",
      "lastname": "White",
      "group": "React N34"
    },
    {
      "id": "aac1",
      "firstname": "Zufarbek",
      "lastname": "Yoldashev",
      "group": "React N34"
    }
  ],
  "teachers": [
    {
      "id": "1",
      "firstname": "John",
      "lastname": "Doe",
      "group": "React N34",
      "level": "Middle"
    },
    {
      "id": "2",
      "firstname": "Tom",
      "lastname": "Smith",
      "group": "React N34",
      "level": "Senior"
    },
    {
      "id": "3",
      "firstname": "John",
      "lastname": "Smith",
      "group": "React N45",
      "level": "Middle"
    },
    {
      "id": "4",
      "firstname": "John",
      "lastname": "White",
      "group": "React N34",
      "level": "Junior"
    },
    {
      "id": "4799",
      "firstname": "Zufarbek",
      "lastname": "Yoldashev",
      "group": "React N45",
      "level": "Junior"
    },
    {
      "id": "bfb7",
      "firstname": "Alex",
      "lastname": "Brown",
      "group": "React N34",
      "level": "Middle"
    }
  ]
}